segmentor/__init__.py
pkg_sydilkupa-0.0.1.dist-info/LICENCE
pkg_sydilkupa-0.0.1.dist-info/METADATA
pkg_sydilkupa-0.0.1.dist-info/WHEEL
pkg_sydilkupa-0.0.1.dist-info/top_level.txt
pkg_sydilkupa-0.0.1.dist-info/RECORD
