Metadata-Version: 2.1
Name: pkg-sydilkupa
Version: 0.0.1
Summary: Packaging a segmentation project
Home-page: https://gitlab.com/sydilkupa/segmentation-and-classification
Author: sydilkupa
Author-email: skupa@ska.ac.za
License: UNKNOWN
Platform: UNKNOWN
Classifier: Programming Language :: Python :: 3
Classifier: License :: OSI Approved :: MIT License
Classifier: Operating System :: OS Independent
Requires-Python: >=3.6
